{
  "project_info": {
    "project_number": "178013335305",
    "project_id": "nolgobulja-2023",
    "storage_bucket": "nolgobulja-2023.appspot.com"
  },
  "client": [
    {
      "client_info": {
        "mobilesdk_app_id": "1:178013335305:android:26cdc5741e50ad63306dd8",
        "android_client_info": {
          "package_name": "com.ppnyy.nolgobulja"
        }
      },
      "oauth_client": [
        {
          "client_id": "178013335305-p5msi2e5l32a4gl6q4g4fo3jrnur934t.apps.googleusercontent.com",
          "client_type": 1,
          "android_info": {
            "package_name": "com.ppnyy.nolgobulja",
            "certificate_hash": "d9157ac5f864158f3598accf4ec33043a3d42dd7"
          }
        },
        {
          "client_id": "178013335305-ubfkbi2cd5g63k66ivhhtitqmc1eiuk4.apps.googleusercontent.com",
          "client_type": 1,
          "android_info": {
            "package_name": "com.ppnyy.nolgobulja",
            "certificate_hash": "be3ee8b250c4b73b3c6d79efe5a18dfb35a86a79"
          }
        },
        {
          "client_id": "178013335305-3tuknh3s2ptb19tstjq4immq3t2rovn6.apps.googleusercontent.com",
          "client_type": 3
        }
      ],
      "api_key": [
        {
          "current_key": "AIzaSyB_lwkRSJ4SgClhy9rDY6jVDcHVuRUXt0w"
        }
      ],
      "services": {
        "appinvite_service": {
          "other_platform_oauth_client": [
            {
              "client_id": "178013335305-3tuknh3s2ptb19tstjq4immq3t2rovn6.apps.googleusercontent.com",
              "client_type": 3
            },
            {
              "client_id": "178013335305-u139pt1c45nv77u97shthoqi2tp0jafv.apps.googleusercontent.com",
              "client_type": 2,
              "ios_info": {
                "bundle_id": "com.ppnyy.nolgobulja"
              }
            }
          ]
        }
      }
    }
  ],
  "configuration_version": "1"
}